pbcommon/FuturesConfig.py
pbcommon/MaxSizeList.py
pbcommon/__init__.py
pbcommon/alerting.py
pbcommon/cmetimezone.py
pbcommon/loggers.py
pbcommon/utils.py
pbcommon/vars.py
tests/__init__.py
tests/test_FuturesConfig.py
tests/test_MaxSizeList.py
tests/test_cmetimezone.py
tests/test_loggers.py
tests/test_utils.py
tests/test_vars.py
pbcommon-0.1.65.dist-info/LICENSE.txt
pbcommon-0.1.65.dist-info/METADATA
pbcommon-0.1.65.dist-info/WHEEL
pbcommon-0.1.65.dist-info/top_level.txt
pbcommon-0.1.65.dist-info/RECORD
